calculator/main.py
calculator_suoxd-0.1.1.dist-info/licenses/LICENSE
calculator_suoxd-0.1.1.dist-info/METADATA
calculator_suoxd-0.1.1.dist-info/WHEEL
calculator_suoxd-0.1.1.dist-info/entry_points.txt
calculator_suoxd-0.1.1.dist-info/top_level.txt
calculator_suoxd-0.1.1.dist-info/RECORD
