Metadata-Version: 2.4
Name: calculator-suoxd
Version: 0.1.1
Summary: A simple calculator for elementary school students to practice addition and subtraction.
Author-email: Zacsuo <suoxd123@126.com>
License: MIT License
Requires-Python: >=3.6
License-File: LICENSE
Dynamic: license-file
